{"title":"Hot Beautiful Sexy Girls Super HD Wallpaper Set 160","uid":12124015,"size":41287047,"categoryP":"other","categoryS":"pictures","magnet":"?xt=urn:btih:031922dbe059ddc80554dc5fe2e53eaa729ad13e&amp;dn=Hot+Beautiful+Sexy+Girls+Super+HD+Wallpaper+Set+160&amp;tr=udp%3A%2F%2Ftracker.openbittorrent.com%3A80&amp;tr=udp%3A%2F%2Fopen.demonii.com%3A1337&amp;tr=udp%3A%2F%2Ftracker.coppersurfer.tk%3A6969&amp;tr=udp%3A%2F%2Fexodus.desync.com%3A6969","seeders":0,"leechers":1,"uploader":"sodebabe","files":27,"time":1436895815,"description":"[b]Hot Beautiful Sexy Girls Super HD Wallpaper Set 160\n\n25 JPG    |    1920x1080   1600 x 1200  | 39 Mb [/b]\n\n &lt;a href=&quot;\nhttp://www.wallhdpic.com/2015/03/jessica-alba-wallpaper_30.html&quot; rel=&quot;nofollow&quot; target=&quot;_NEW&quot;&gt;\nhttp://www.wallhdpic.com/2015/03/jessica-alba-wallpaper_30.html&lt;/a&gt;\n &lt;a href=&quot;\nhttp://www.wallhdpic.com/2015/03/eliza-dushku-hair-wallpaper.html&quot; rel=&quot;nofollow&quot; target=&quot;_NEW&quot;&gt;\nhttp://www.wallhdpic.com/2015/03/eliza-dushku-hair-wallpaper.html&lt;/a&gt;\n &lt;a href=&quot;\nhttp://www.wallhdpic.com/2015/01/elisha-cuthbert-wallpaper.html&quot; rel=&quot;nofollow&quot; target=&quot;_NEW&quot;&gt;\nhttp://www.wallhdpic.com/2015/01/elisha-cuthbert-wallpaper.html&lt;/a&gt;\n &lt;a href=&quot;\nhttp://www.wallhdpic.com/2015/03/alexis-bledel-eyes-wallpaper.html&quot; rel=&quot;nofollow&quot; target=&quot;_NEW&quot;&gt;\nhttp://www.wallhdpic.com/2015/03/alexis-bledel-eyes-wallpaper.html&lt;/a&gt;","torrent":{"xt":"urn:btih:031922dbe059ddc80554dc5fe2e53eaa729ad13e","amp;dn":"Hot+Beautiful+Sexy+Girls+Super+HD+Wallpaper+Set+160","amp;tr":["udp%3A%2F%2Ftracker.openbittorrent.com%3A80","udp%3A%2F%2Fopen.demonii.com%3A1337","udp%3A%2F%2Ftracker.coppersurfer.tk%3A6969","udp%3A%2F%2Fexodus.desync.com%3A6969"],"infoHash":"031922dbe059ddc80554dc5fe2e53eaa729ad13e","infoHashBuffer":{"type":"Buffer","data":[3,25,34,219,224,89,221,200,5,84,220,95,226,229,62,170,114,154,209,62]},"announce":[],"urlList":[]}}