{"title":"Trine 3: The Artifacts of Power","uid":12261305,"size":4459753726,"categoryP":"games","categoryS":"pc","magnet":"?xt=urn:btih:2506e9a80a0894aa370a02eb92362be1847f93b3&amp;dn=Trine+3%3A+The+Artifacts+of+Power&amp;tr=udp%3A%2F%2Ftracker.openbittorrent.com%3A80&amp;tr=udp%3A%2F%2Fopen.demonii.com%3A1337&amp;tr=udp%3A%2F%2Ftracker.coppersurfer.tk%3A6969&amp;tr=udp%3A%2F%2Fexodus.desync.com%3A6969","seeders":0,"leechers":1,"uploader":"polan32","files":4,"time":1440173607,"description":"Title: Trine 3: The Artifacts of Power\nGenre: Action, Adventure, Indie\nDeveloper: Frozenbyte \nPublisher: Frozenbyte\t\nRelease Date: 20 Aug, 2015\nCrack: 3DM\n\nSystem Requirements: \nOS: (64 bit / 32 bit *) Windows 10 / 8 / 7 / Vista \nProcessor: Intel Core i3/i5/i7 1.8 GHz CPU dual-core. AMD 2.0 GHz dual-core. \nMemory: 4 GB RAM \nGraphics: NVIDIA GeForce 260 / Radeon HD 4000 Series / Intel HD Graphics 4000 \nDirectX: Version 10 \n\nAbout This Game\nExperience a fairytale world of breathtaking sceneries and face a myriad of physics-based puzzles, wonderful contraptions, dangerous foes and enchanting creatures. \n\nTrine 3: The Artifacts of Power is a platforming game of action, puzzles and adventure, and the sequel to the award winning Trine and Trine 2. Reunite with the familiar heroes - Pontius the Knight, Amadeus the Wizard and Zoya the Thief in an all-new adventure, now for the first time in full 3D! \n\nPlayable in single-player or in co-up with up to three players, both locally or online.\n \n\nInstall &amp; Play","torrent":{"xt":"urn:btih:2506e9a80a0894aa370a02eb92362be1847f93b3","amp;dn":"Trine+3%3A+The+Artifacts+of+Power","amp;tr":["udp%3A%2F%2Ftracker.openbittorrent.com%3A80","udp%3A%2F%2Fopen.demonii.com%3A1337","udp%3A%2F%2Ftracker.coppersurfer.tk%3A6969","udp%3A%2F%2Fexodus.desync.com%3A6969"],"infoHash":"2506e9a80a0894aa370a02eb92362be1847f93b3","infoHashBuffer":{"type":"Buffer","data":[37,6,233,168,10,8,148,170,55,10,2,235,146,54,43,225,132,127,147,179]},"announce":[],"urlList":[]}}