{"title":"[TabooTrannys] Monique and Pierre - Tranny Part 2","uid":12177172,"size":171246387,"categoryP":"porn","categoryS":"movie_clips","magnet":"?xt=urn:btih:353302391aae9b649c2071f36982ccb1609ef093&amp;dn=%5BTabooTrannys%5D+Monique+and+Pierre+-+Tranny+Part+2&amp;tr=udp%3A%2F%2Ftracker.openbittorrent.com%3A80&amp;tr=udp%3A%2F%2Fopen.demonii.com%3A1337&amp;tr=udp%3A%2F%2Ftracker.coppersurfer.tk%3A6969&amp;tr=udp%3A%2F%2Fexodus.desync.com%3A6969","seeders":0,"leechers":1,"uploader":"HighCode","files":1,"time":1438341248,"description":"[TabooTrannys] Monique and Pierre - Tranny Part 2\n\nScreenshots: &lt;a href=&quot;\nhttp://imgclover.com/image/Elo&quot; rel=&quot;nofollow&quot; target=&quot;_NEW&quot;&gt;\nhttp://imgclover.com/image/Elo&lt;/a&gt; &lt;a href=&quot;\nhttp://imgclover.com/image/ElF&quot; rel=&quot;nofollow&quot; target=&quot;_NEW&quot;&gt;\nhttp://imgclover.com/image/ElF&lt;/a&gt;","torrent":{"xt":"urn:btih:353302391aae9b649c2071f36982ccb1609ef093","amp;dn":"%5BTabooTrannys%5D+Monique+and+Pierre+-+Tranny+Part+2","amp;tr":["udp%3A%2F%2Ftracker.openbittorrent.com%3A80","udp%3A%2F%2Fopen.demonii.com%3A1337","udp%3A%2F%2Ftracker.coppersurfer.tk%3A6969","udp%3A%2F%2Fexodus.desync.com%3A6969"],"infoHash":"353302391aae9b649c2071f36982ccb1609ef093","infoHashBuffer":{"type":"Buffer","data":[53,51,2,57,26,174,155,100,156,32,113,243,105,130,204,177,96,158,240,147]},"announce":[],"urlList":[]}}