{"title":"Isabel S02 E04 - Hardcoded Eng Subs - Sno","uid":12190418,"size":600080962,"categoryP":"video","categoryS":"tv_shows","magnet":"?xt=urn:btih:6b4594ce85450247acfacbcb4df0424a683f484f&amp;dn=Isabel+S02+E04+-+Hardcoded+Eng+Subs+-+Sno&amp;tr=udp%3A%2F%2Ftracker.openbittorrent.com%3A80&amp;tr=udp%3A%2F%2Fopen.demonii.com%3A1337&amp;tr=udp%3A%2F%2Ftracker.coppersurfer.tk%3A6969&amp;tr=udp%3A%2F%2Fexodus.desync.com%3A6969","seeders":0,"leechers":1,"uploader":"Snowhiter","files":3,"time":1438639859,"description":"Isabel S02 E04 - Hardcoded Eng Subs - Sno\n\nIt's Queen Isabel's birthday, but she fears for her daughter's safety. Fernando thinks she is being too tough on traitors.\n\nVideo 852 x 480 / 25 fps / 947 kbps / Mp4\n\nAudio 128 kbps AAC\n\nDuration 1:13\n\nSeed to the Max - Muchas gracias . . .\n\nSno","torrent":{"xt":"urn:btih:6b4594ce85450247acfacbcb4df0424a683f484f","amp;dn":"Isabel+S02+E04+-+Hardcoded+Eng+Subs+-+Sno","amp;tr":["udp%3A%2F%2Ftracker.openbittorrent.com%3A80","udp%3A%2F%2Fopen.demonii.com%3A1337","udp%3A%2F%2Ftracker.coppersurfer.tk%3A6969","udp%3A%2F%2Fexodus.desync.com%3A6969"],"infoHash":"6b4594ce85450247acfacbcb4df0424a683f484f","infoHashBuffer":{"type":"Buffer","data":[107,69,148,206,133,69,2,71,172,250,203,203,77,240,66,74,104,63,72,79]},"announce":[],"urlList":[]}}