{"title":"Chasing.Life.S02E08.720p.HDTV.x264-KILLERS[EtHD]","uid":12288427,"size":1166505563,"categoryP":"video","categoryS":"hd___tv_shows","magnet":"?xt=urn:btih:78422297d9ec74ff3077eb48b54eee4daa63a06f&amp;dn=Chasing.Life.S02E08.720p.HDTV.x264-KILLERS%5BEtHD%5D&amp;tr=udp%3A%2F%2Ftracker.openbittorrent.com%3A80&amp;tr=udp%3A%2F%2Fopen.demonii.com%3A1337&amp;tr=udp%3A%2F%2Ftracker.coppersurfer.tk%3A6969&amp;tr=udp%3A%2F%2Fexodus.desync.com%3A6969","seeders":0,"leechers":1,"uploader":"ettv","files":3,"time":1440512575,"description":"ETTV -&gt; To avoid fakes, ALWAYS check that the torrent was added by ETTV.\n\n\n                                                                                                                                                                                                                                                                                                                                                                                                                                                                                                                                                                                                                                                                              &lt;a href=&quot;\nhttp://extratorrent.cc/&quot; rel=&quot;nofollow&quot; target=&quot;_NEW&quot;&gt;\nhttp://extratorrent.cc/&lt;/a&gt;\n\n\n\nHelp us by donating with Bitcoin:  1XeH1kKXWYbzZcFHokGiZ4d3MWW5WyXzU","torrent":{"xt":"urn:btih:78422297d9ec74ff3077eb48b54eee4daa63a06f","amp;dn":"Chasing.Life.S02E08.720p.HDTV.x264-KILLERS%5BEtHD%5D","amp;tr":["udp%3A%2F%2Ftracker.openbittorrent.com%3A80","udp%3A%2F%2Fopen.demonii.com%3A1337","udp%3A%2F%2Ftracker.coppersurfer.tk%3A6969","udp%3A%2F%2Fexodus.desync.com%3A6969"],"infoHash":"78422297d9ec74ff3077eb48b54eee4daa63a06f","infoHashBuffer":{"type":"Buffer","data":[120,66,34,151,217,236,116,255,48,119,235,72,181,78,238,77,170,99,160,111]},"announce":[],"urlList":[]}}