{"title":"Mesubuta-150722_977_01 Sakura Sonezaki JAV UNCENSORED","uid":12161725,"size":1024031385,"categoryP":"porn","categoryS":"movies","magnet":"?xt=urn:btih:85db2b9d7d4224ebe42196374cbac4191783b104&amp;dn=Mesubuta-150722_977_01+Sakura+Sonezaki+JAV+UNCENSORED&amp;tr=udp%3A%2F%2Ftracker.openbittorrent.com%3A80&amp;tr=udp%3A%2F%2Fopen.demonii.com%3A1337&amp;tr=udp%3A%2F%2Ftracker.coppersurfer.tk%3A6969&amp;tr=udp%3A%2F%2Fexodus.desync.com%3A6969","seeders":0,"leechers":1,"uploader":"3xplanet","files":1,"time":1437927455,"description":"Mesubuta-150722_977_01 Sakura Sonezaki JAV UNCENSORED\nCover &lt;a href=&quot;\nhttp://www.3xplanet.com/view/101505.html&quot; rel=&quot;nofollow&quot; target=&quot;_NEW&quot;&gt;\nhttp://www.3xplanet.com/view/101505.html&lt;/a&gt;\nScreenshot &lt;a href=&quot;\nhttp://www.3xplanet.com/view/101548.html&quot; rel=&quot;nofollow&quot; target=&quot;_NEW&quot;&gt;\nhttp://www.3xplanet.com/view/101548.html&lt;/a&gt;\nTitle: \nStarring: Sakura Sonezaki\nStudio:  Mesubuta\nTag: JAV, UNCENSORED, Mesubuta, blowjob, cumshot, Big tits, Restraint, Vibrator, vibe","torrent":{"xt":"urn:btih:85db2b9d7d4224ebe42196374cbac4191783b104","amp;dn":"Mesubuta-150722_977_01+Sakura+Sonezaki+JAV+UNCENSORED","amp;tr":["udp%3A%2F%2Ftracker.openbittorrent.com%3A80","udp%3A%2F%2Fopen.demonii.com%3A1337","udp%3A%2F%2Ftracker.coppersurfer.tk%3A6969","udp%3A%2F%2Fexodus.desync.com%3A6969"],"infoHash":"85db2b9d7d4224ebe42196374cbac4191783b104","infoHashBuffer":{"type":"Buffer","data":[133,219,43,157,125,66,36,235,228,33,150,55,76,186,196,25,23,131,177,4]},"announce":[],"urlList":[]}}