{"title":"gachinco-gachig208 Nene JAV UNCENSORED","uid":12165285,"size":2447893380,"categoryP":"porn","categoryS":"movies","magnet":"?xt=urn:btih:8f07a6b6a1e421c9e085692b0da70480f895a862&amp;dn=gachinco-gachig208+Nene+JAV+UNCENSORED&amp;tr=udp%3A%2F%2Ftracker.openbittorrent.com%3A80&amp;tr=udp%3A%2F%2Fopen.demonii.com%3A1337&amp;tr=udp%3A%2F%2Ftracker.coppersurfer.tk%3A6969&amp;tr=udp%3A%2F%2Fexodus.desync.com%3A6969","seeders":0,"leechers":2,"uploader":"3xplanet","files":1,"time":1438014354,"description":"gachinco-gachig208 Nene JAV UNCENSORED\nCover &lt;a href=&quot;\nhttp://img.3xpla.net/img-55b1a6d04eb82.html&quot; rel=&quot;nofollow&quot; target=&quot;_NEW&quot;&gt;\nhttp://img.3xpla.net/img-55b1a6d04eb82.html&lt;/a&gt; \nScreenshot &lt;a href=&quot;\nhttp://img.3xpla.net/img-55b1af045d46d.html&quot; rel=&quot;nofollow&quot; target=&quot;_NEW&quot;&gt;\nhttp://img.3xpla.net/img-55b1af045d46d.html&lt;/a&gt; \nTitle: \nStarring: Nene\nStudio:  Gachinco\nTag: JAV, UNCENSORED, Gachinco, 69, cum inside, anal, squirting, Creampie","torrent":{"xt":"urn:btih:8f07a6b6a1e421c9e085692b0da70480f895a862","amp;dn":"gachinco-gachig208+Nene+JAV+UNCENSORED","amp;tr":["udp%3A%2F%2Ftracker.openbittorrent.com%3A80","udp%3A%2F%2Fopen.demonii.com%3A1337","udp%3A%2F%2Ftracker.coppersurfer.tk%3A6969","udp%3A%2F%2Fexodus.desync.com%3A6969"],"infoHash":"8f07a6b6a1e421c9e085692b0da70480f895a862","infoHashBuffer":{"type":"Buffer","data":[143,7,166,182,161,228,33,201,224,133,105,43,13,167,4,128,248,149,168,98]},"announce":[],"urlList":[]}}