{"title":"moby-extreme ways.mp3","uid":12248129,"size":9488976,"categoryP":"audio","categoryS":"music","magnet":"?xt=urn:btih:8fe2fcebab2ec13a10b851e0a860ec0b22507f61&amp;dn=moby-extreme+ways.mp3&amp;tr=udp%3A%2F%2Ftracker.openbittorrent.com%3A80&amp;tr=udp%3A%2F%2Fopen.demonii.com%3A1337&amp;tr=udp%3A%2F%2Ftracker.coppersurfer.tk%3A6969&amp;tr=udp%3A%2F%2Fexodus.desync.com%3A6969","seeders":0,"leechers":0,"uploader":"karter124","files":1,"time":1439956314,"description":"moby-extreme ways","torrent":{"xt":"urn:btih:8fe2fcebab2ec13a10b851e0a860ec0b22507f61","amp;dn":"moby-extreme+ways.mp3","amp;tr":["udp%3A%2F%2Ftracker.openbittorrent.com%3A80","udp%3A%2F%2Fopen.demonii.com%3A1337","udp%3A%2F%2Ftracker.coppersurfer.tk%3A6969","udp%3A%2F%2Fexodus.desync.com%3A6969"],"infoHash":"8fe2fcebab2ec13a10b851e0a860ec0b22507f61","infoHashBuffer":{"type":"Buffer","data":[143,226,252,235,171,46,193,58,16,184,81,224,168,96,236,11,34,80,127,97]},"announce":[],"urlList":[]}}