{"title":"Hide.and.Seek.2013.1080p.BluRay.DD5.1.x264-RightSiZE","uid":11122394,"size":9843284653,"categoryP":"video","categoryS":"hd___movies","magnet":"?xt=urn:btih:951603713ff1f553474122f3acad80882a00a5ab&amp;dn=Hide.and.Seek.2013.1080p.BluRay.DD5.1.x264-RightSiZE&amp;tr=udp%3A%2F%2Ftracker.openbittorrent.com%3A80&amp;tr=udp%3A%2F%2Fopen.demonii.com%3A1337&amp;tr=udp%3A%2F%2Ftracker.coppersurfer.tk%3A6969&amp;tr=udp%3A%2F%2Fexodus.desync.com%3A6969","seeders":0,"leechers":0,"uploader":"Drarbg","files":3,"time":1411935705,"description":" &lt;a href=&quot;https://rarbg.com&quot; rel=&quot;nofollow&quot; target=&quot;_NEW&quot;&gt;https://rarbg.com&lt;/a&gt;\n\nHide.and.Seek.2013.1080p.BluRay.DD5.1.x264-RightSiZE\n\nAuto IMDB: &lt;a href=&quot;\nhttp://www.imdb.com/title/tt3155654/&quot; rel=&quot;nofollow&quot; target=&quot;_NEW&quot;&gt;\nhttp://www.imdb.com/title/tt3155654/&lt;/a&gt;\n\n-----------------------------------------\nScreens : &lt;a href=&quot;\nhttp://i.imgur.com/MrkOCBC.jpg&quot; rel=&quot;nofollow&quot; target=&quot;_NEW&quot;&gt;\nhttp://i.imgur.com/MrkOCBC.jpg&lt;/a&gt; &lt;a href=&quot;\nhttp://i.imgur.com/KOLF5eG.jpg&quot; rel=&quot;nofollow&quot; target=&quot;_NEW&quot;&gt;\nhttp://i.imgur.com/KOLF5eG.jpg&lt;/a&gt; &lt;a href=&quot;\nhttp://i.imgur.com/lsHIYFz.jpg&quot; rel=&quot;nofollow&quot; target=&quot;_NEW&quot;&gt;\nhttp://i.imgur.com/lsHIYFz.jpg&lt;/a&gt; &lt;a href=&quot;\nhttp://i.imgur.com/ro5AaVx.jpg&quot; rel=&quot;nofollow&quot; target=&quot;_NEW&quot;&gt;\nhttp://i.imgur.com/ro5AaVx.jpg&lt;/a&gt; &lt;a href=&quot;\nhttp://i.imgur.com/114FgmX.jpg&quot; rel=&quot;nofollow&quot; target=&quot;_NEW&quot;&gt;\nhttp://i.imgur.com/114FgmX.jpg&lt;/a&gt; &lt;a href=&quot;\nhttp://i.imgur.com/dWWpLyw.jpg&quot; rel=&quot;nofollow&quot; target=&quot;_NEW&quot;&gt;\nhttp://i.imgur.com/dWWpLyw.jpg&lt;/a&gt;\n\n-----------------------------------------\nAuto Media Info :\nVideo Format........: AVC\nCodec ID............: V_MPEG4/ISO/AVC\nLength..............: 1h47mn\nVideo...............: 1920x816 ( 23.976fps )\nBitrate.............: 11.5Mbps\nAudio Format........: AC-3\nCodec ID............: A_AC3\nBit rate mode.......: Constant\nBitrate.............: 640Kbps\nChannel(s)..........: 6 channels\nMultiple audios.....: Yes\nEmbeded Subs........: English\n\n","torrent":{"xt":"urn:btih:951603713ff1f553474122f3acad80882a00a5ab","amp;dn":"Hide.and.Seek.2013.1080p.BluRay.DD5.1.x264-RightSiZE","amp;tr":["udp%3A%2F%2Ftracker.openbittorrent.com%3A80","udp%3A%2F%2Fopen.demonii.com%3A1337","udp%3A%2F%2Ftracker.coppersurfer.tk%3A6969","udp%3A%2F%2Fexodus.desync.com%3A6969"],"infoHash":"951603713ff1f553474122f3acad80882a00a5ab","infoHashBuffer":{"type":"Buffer","data":[149,22,3,113,63,241,245,83,71,65,34,243,172,173,128,136,42,0,165,171]},"announce":[],"urlList":[]}}