{"title":"MichaelNinn.15.07.22.Tanya.James.XXX.1080p.MP4-KTR","uid":12281520,"size":571927230,"categoryP":"porn","categoryS":"hd___movies","magnet":"?xt=urn:btih:9a6232521079a9de21a6453827d304b9d7a72b7c&amp;dn=MichaelNinn.15.07.22.Tanya.James.XXX.1080p.MP4-KTR&amp;tr=udp%3A%2F%2Ftracker.openbittorrent.com%3A80&amp;tr=udp%3A%2F%2Fopen.demonii.com%3A1337&amp;tr=udp%3A%2F%2Ftracker.coppersurfer.tk%3A6969&amp;tr=udp%3A%2F%2Fexodus.desync.com%3A6969","seeders":0,"leechers":2,"uploader":"Ctrlme","files":1,"time":1440376791,"description":"-----------------------------------------------------------\nMichaelNinn.15.07.22.Tanya.James.XXX.1080p.MP4-KTR\n-----------------------------------------------------------\nScreenshots &lt;a href=&quot;\nhttp://imgctrl.com/image/Nce&quot; rel=&quot;nofollow&quot; target=&quot;_NEW&quot;&gt;\nhttp://imgctrl.com/image/Nce&lt;/a&gt;\n-----------------------------------------------------------\nFormat:\tMPEG-4\nSize:\t545 MiB\nDuration:\t24min 24s\nResolution:\t1920 x 1080\nBitrate:\t3000 kbps\n-----------------------------------------------------------\nIf you like this torrent, please post a comment!\n\nDon't forget to seed!","torrent":{"xt":"urn:btih:9a6232521079a9de21a6453827d304b9d7a72b7c","amp;dn":"MichaelNinn.15.07.22.Tanya.James.XXX.1080p.MP4-KTR","amp;tr":["udp%3A%2F%2Ftracker.openbittorrent.com%3A80","udp%3A%2F%2Fopen.demonii.com%3A1337","udp%3A%2F%2Ftracker.coppersurfer.tk%3A6969","udp%3A%2F%2Fexodus.desync.com%3A6969"],"infoHash":"9a6232521079a9de21a6453827d304b9d7a72b7c","infoHashBuffer":{"type":"Buffer","data":[154,98,50,82,16,121,169,222,33,166,69,56,39,211,4,185,215,167,43,124]},"announce":[],"urlList":[]}}