{"title":"X-Men.Days.Of.Future.Past.2014.DVDRip.x264-VETO","uid":11075052,"size":979584957,"categoryP":"video","categoryS":"movies","magnet":"?xt=urn:btih:a2019720c72d57bd26e69acba78ff84bbcc16f62&amp;dn=X-Men.Days.Of.Future.Past.2014.DVDRip.x264-VETO&amp;tr=udp%3A%2F%2Ftracker.openbittorrent.com%3A80&amp;tr=udp%3A%2F%2Fopen.demonii.com%3A1337&amp;tr=udp%3A%2F%2Ftracker.coppersurfer.tk%3A6969&amp;tr=udp%3A%2F%2Fexodus.desync.com%3A6969","seeders":0,"leechers":0,"uploader":"Drarbg","files":5,"time":1411323705,"description":" &lt;a href=&quot;https://rarbg.com&quot; rel=&quot;nofollow&quot; target=&quot;_NEW&quot;&gt;https://rarbg.com&lt;/a&gt;\n\nX-Men.Days.Of.Future.Past.2014.DVDRip.x264-VETO\n\nAuto IMDB: &lt;a href=&quot;\nhttp://www.imdb.com/title/tt1877832/&quot; rel=&quot;nofollow&quot; target=&quot;_NEW&quot;&gt;\nhttp://www.imdb.com/title/tt1877832/&lt;/a&gt;\n\n-----------------------------------------\nScreens : &lt;a href=&quot;\nhttp://imagecurl.org/viewer.php?file=04545416883027631456.jpg&quot; rel=&quot;nofollow&quot; target=&quot;_NEW&quot;&gt;\nhttp://imagecurl.org/viewer.php?file=04545416883027631456.jpg&lt;/a&gt;\n\n-----------------------------------------\nAuto Media Info :\nVideo Format........: AVC\nCodec ID............: V_MPEG4/ISO/AVC\nLength..............: 2h6mn\nVideo...............: 720x290 ( 25.000fps )\nAudio Format........: AAC\nCodec ID............: A_AAC\nChannel(s)..........: 2 channels\n\n","torrent":{"xt":"urn:btih:a2019720c72d57bd26e69acba78ff84bbcc16f62","amp;dn":"X-Men.Days.Of.Future.Past.2014.DVDRip.x264-VETO","amp;tr":["udp%3A%2F%2Ftracker.openbittorrent.com%3A80","udp%3A%2F%2Fopen.demonii.com%3A1337","udp%3A%2F%2Ftracker.coppersurfer.tk%3A6969","udp%3A%2F%2Fexodus.desync.com%3A6969"],"infoHash":"a2019720c72d57bd26e69acba78ff84bbcc16f62","infoHashBuffer":{"type":"Buffer","data":[162,1,151,32,199,45,87,189,38,230,154,203,167,143,248,75,188,193,111,98]},"announce":[],"urlList":[]}}