{"title":"PureMature - Alix Lynx ** NEW 18 july 2015 ** [.mp4]","uid":12138998,"size":258523816,"categoryP":"porn","categoryS":"movies_dvdr","magnet":"?xt=urn:btih:aba1e79847d44221d5683b3fc9d53fb6d2fbeec2&amp;dn=+PureMature+-+Alix+Lynx+%2A%2A+NEW+18+july+2015+%2A%2A+%5B.mp4%5D&amp;tr=udp%3A%2F%2Ftracker.openbittorrent.com%3A80&amp;tr=udp%3A%2F%2Fopen.demonii.com%3A1337&amp;tr=udp%3A%2F%2Ftracker.coppersurfer.tk%3A6969&amp;tr=udp%3A%2F%2Fexodus.desync.com%3A6969","seeders":0,"leechers":1,"uploader":"TKTh3K1ng","files":1,"time":1437304754,"description":"Screenshots:\n &lt;a href=&quot;\nhttp://imgsking.com/image/bo&quot; rel=&quot;nofollow&quot; target=&quot;_NEW&quot;&gt;\nhttp://imgsking.com/image/bo&lt;/a&gt;\n &lt;a href=&quot;\nhttp://imgsking.com/image/by&quot; rel=&quot;nofollow&quot; target=&quot;_NEW&quot;&gt;\nhttp://imgsking.com/image/by&lt;/a&gt;","torrent":{"xt":"urn:btih:aba1e79847d44221d5683b3fc9d53fb6d2fbeec2","amp;dn":"+PureMature+-+Alix+Lynx+%2A%2A+NEW+18+july+2015+%2A%2A+%5B.mp4%5D","amp;tr":["udp%3A%2F%2Ftracker.openbittorrent.com%3A80","udp%3A%2F%2Fopen.demonii.com%3A1337","udp%3A%2F%2Ftracker.coppersurfer.tk%3A6969","udp%3A%2F%2Fexodus.desync.com%3A6969"],"infoHash":"aba1e79847d44221d5683b3fc9d53fb6d2fbeec2","infoHashBuffer":{"type":"Buffer","data":[171,161,231,152,71,212,66,33,213,104,59,63,201,213,63,182,210,251,238,194]},"announce":[],"urlList":[]}}