{"title":"Fairy Tail - 200 [FlyH] vostfr 1080p.mp4","uid":11071291,"size":485551340,"categoryP":"video","categoryS":"other","magnet":"?xt=urn:btih:be69748fb735b57e908ca7486b61dff88ac31960&amp;dn=Fairy+Tail+-+200+%5BFlyH%5D+vostfr+1080p.mp4&amp;tr=udp%3A%2F%2Ftracker.openbittorrent.com%3A80&amp;tr=udp%3A%2F%2Fopen.demonii.com%3A1337&amp;tr=udp%3A%2F%2Ftracker.coppersurfer.tk%3A6969&amp;tr=udp%3A%2F%2Fexodus.desync.com%3A6969","seeders":0,"leechers":0,"uploader":null,"files":1,"time":1411272613,"description":"Fairy Tail - 200 [FlyH] vostfr 1080p.mp4","torrent":{"xt":"urn:btih:be69748fb735b57e908ca7486b61dff88ac31960","amp;dn":"Fairy+Tail+-+200+%5BFlyH%5D+vostfr+1080p.mp4","amp;tr":["udp%3A%2F%2Ftracker.openbittorrent.com%3A80","udp%3A%2F%2Fopen.demonii.com%3A1337","udp%3A%2F%2Ftracker.coppersurfer.tk%3A6969","udp%3A%2F%2Fexodus.desync.com%3A6969"],"infoHash":"be69748fb735b57e908ca7486b61dff88ac31960","infoHashBuffer":{"type":"Buffer","data":[190,105,116,143,183,53,181,126,144,140,167,72,107,97,223,248,138,195,25,96]},"announce":[],"urlList":[]}}