{"title":"Raymond Franz-Crisis of Consience","uid":12212042,"size":7456450,"categoryP":"other","categoryS":"e_books","magnet":"?xt=urn:btih:bfc2599d743576267caa4beab81b49b609488f6b&amp;dn=Raymond+Franz-Crisis+of+Consience&amp;tr=udp%3A%2F%2Ftracker.openbittorrent.com%3A80&amp;tr=udp%3A%2F%2Fopen.demonii.com%3A1337&amp;tr=udp%3A%2F%2Ftracker.coppersurfer.tk%3A6969&amp;tr=udp%3A%2F%2Fexodus.desync.com%3A6969","seeders":0,"leechers":0,"uploader":null,"files":2,"time":1439119547,"description":"This is the first book by Raymond Franz, a former Jehovah Witnesses' Governing Body member.\nThe book reveals the inner workings and structure of this organization","torrent":{"xt":"urn:btih:bfc2599d743576267caa4beab81b49b609488f6b","amp;dn":"Raymond+Franz-Crisis+of+Consience","amp;tr":["udp%3A%2F%2Ftracker.openbittorrent.com%3A80","udp%3A%2F%2Fopen.demonii.com%3A1337","udp%3A%2F%2Ftracker.coppersurfer.tk%3A6969","udp%3A%2F%2Fexodus.desync.com%3A6969"],"infoHash":"bfc2599d743576267caa4beab81b49b609488f6b","infoHashBuffer":{"type":"Buffer","data":[191,194,89,157,116,53,118,38,124,170,75,234,184,27,73,182,9,72,143,107]},"announce":[],"urlList":[]}}