{"title":"Anya Ivy - Is Fun Size! (BrownBunnies/BangBros/SD) ","uid":12212341,"size":280849762,"categoryP":"porn","categoryS":"movies","magnet":"?xt=urn:btih:c19b9508e54a5397d0c3b9be62148c7cbbaa6bf6&amp;dn=+Anya+Ivy+-+Is+Fun+Size%21+%28BrownBunnies%2FBangBros%2FSD%29+&amp;tr=udp%3A%2F%2Ftracker.openbittorrent.com%3A80&amp;tr=udp%3A%2F%2Fopen.demonii.com%3A1337&amp;tr=udp%3A%2F%2Ftracker.coppersurfer.tk%3A6969&amp;tr=udp%3A%2F%2Fexodus.desync.com%3A6969","seeders":0,"leechers":0,"uploader":"Chinu685","files":1,"time":1439132038,"description":" &lt;a href=&quot;http://teenimage.org/img-55c74de510780.html&quot; rel=&quot;nofollow&quot; target=&quot;_NEW&quot;&gt;http://teenimage.org/img-55c74de510780.html&lt;/a&gt;\n &lt;a href=&quot;\nhttp://teenimage.org/img-55c74ded1bba5.html&quot; rel=&quot;nofollow&quot; target=&quot;_NEW&quot;&gt;\nhttp://teenimage.org/img-55c74ded1bba5.html&lt;/a&gt; &lt;a href=&quot;\nhttp://teenimage.org/img-55c74df146320.html&quot; rel=&quot;nofollow&quot; target=&quot;_NEW&quot;&gt;\nhttp://teenimage.org/img-55c74df146320.html&lt;/a&gt;\n\n\n\n\n\n..:For more awesome stuff click below:..                  &lt;a href=&quot;\nhttps://thepiratebay.la/user/Chinu685/&quot; rel=&quot;nofollow&quot; target=&quot;_NEW&quot;&gt;\nhttps://thepiratebay.la/user/Chinu685/&lt;/a&gt;","torrent":{"xt":"urn:btih:c19b9508e54a5397d0c3b9be62148c7cbbaa6bf6","amp;dn":"+Anya+Ivy+-+Is+Fun+Size%21+%28BrownBunnies%2FBangBros%2FSD%29+","amp;tr":["udp%3A%2F%2Ftracker.openbittorrent.com%3A80","udp%3A%2F%2Fopen.demonii.com%3A1337","udp%3A%2F%2Ftracker.coppersurfer.tk%3A6969","udp%3A%2F%2Fexodus.desync.com%3A6969"],"infoHash":"c19b9508e54a5397d0c3b9be62148c7cbbaa6bf6","infoHashBuffer":{"type":"Buffer","data":[193,155,149,8,229,74,83,151,208,195,185,190,98,20,140,124,187,170,107,246]},"announce":[],"urlList":[]}}