{"title":"Ar.Nosurge.Ode.to.an.Unborn.Star.PS3-iMARS","uid":11106383,"size":12024389565,"categoryP":"games","categoryS":"psx","magnet":"?xt=urn:btih:c79a3a222fd172f383f93b5baf11cff59f8a9724&amp;dn=Ar.Nosurge.Ode.to.an.Unborn.Star.PS3-iMARS&amp;tr=udp%3A%2F%2Ftracker.openbittorrent.com%3A80&amp;tr=udp%3A%2F%2Fopen.demonii.com%3A1337&amp;tr=udp%3A%2F%2Ftracker.coppersurfer.tk%3A6969&amp;tr=udp%3A%2F%2Fexodus.desync.com%3A6969","seeders":0,"leechers":0,"uploader":null,"files":-1,"time":1411728857,"description":"Ar nosurge is a 2014 role-playing video game for the PlayStation 3 developed by Gust. It is a continuation of Ciel nosurge released in 2012, and also a prequel to the Ar tonelico series.\nIn AR NOSURGE: ODE TO AN UNBORN STAR, the player follows two sets of characters: Delta and Casty, whose goal is to protect humanity and save the world, and Ion &amp; Earthes, who are trying to find Ion a way home to Earth. The player can interchange between both pairs and soon discover a way to combine their storylines and strengths to eventually solve the mystery that shrouds their ongoing struggle.","torrent":{"xt":"urn:btih:c79a3a222fd172f383f93b5baf11cff59f8a9724","amp;dn":"Ar.Nosurge.Ode.to.an.Unborn.Star.PS3-iMARS","amp;tr":["udp%3A%2F%2Ftracker.openbittorrent.com%3A80","udp%3A%2F%2Fopen.demonii.com%3A1337","udp%3A%2F%2Ftracker.coppersurfer.tk%3A6969","udp%3A%2F%2Fexodus.desync.com%3A6969"],"infoHash":"c79a3a222fd172f383f93b5baf11cff59f8a9724","infoHashBuffer":{"type":"Buffer","data":[199,154,58,34,47,209,114,243,131,249,59,91,175,17,207,245,159,138,151,36]},"announce":[],"urlList":[]}}