{"title":"Furious 7 (2015) EXTENDED BluRay 1080p Ganool","uid":12149054,"size":1931455315,"categoryP":"video","categoryS":"movies","magnet":"?xt=urn:btih:c8a641d3d313c5a2cab604dd8aaf4d051c7c6877&amp;dn=Furious+7+%282015%29+EXTENDED+BluRay+1080p+Ganool&amp;tr=udp%3A%2F%2Ftracker.openbittorrent.com%3A80&amp;tr=udp%3A%2F%2Fopen.demonii.com%3A1337&amp;tr=udp%3A%2F%2Ftracker.coppersurfer.tk%3A6969&amp;tr=udp%3A%2F%2Fexodus.desync.com%3A6969","seeders":0,"leechers":1,"uploader":"santicaz","files":2,"time":1437558302,"description":"Info: http://www.imdb.com/title/tt2820852/\nRelease Date: 3 April 2015 (USA)\nGenre: Action | Crime | Thriller\nStars: Vin Diesel, Paul Walker, Dwayne Johnson\nQuality: EXTENDED BluRay 1080p\nEncoder: SHQ@Ganool\nSource: EXTENDED 1080p BluRay x264-SPARKS\nSubtitle: English\n\n\nSynopsis:\n\nDeckard Shaw seeks revenge against Dominic Toretto and his family for the death of his brother","torrent":{"xt":"urn:btih:c8a641d3d313c5a2cab604dd8aaf4d051c7c6877","amp;dn":"Furious+7+%282015%29+EXTENDED+BluRay+1080p+Ganool","amp;tr":["udp%3A%2F%2Ftracker.openbittorrent.com%3A80","udp%3A%2F%2Fopen.demonii.com%3A1337","udp%3A%2F%2Ftracker.coppersurfer.tk%3A6969","udp%3A%2F%2Fexodus.desync.com%3A6969"],"infoHash":"c8a641d3d313c5a2cab604dd8aaf4d051c7c6877","infoHashBuffer":{"type":"Buffer","data":[200,166,65,211,211,19,197,162,202,182,4,221,138,175,77,5,28,124,104,119]},"announce":[],"urlList":[]}}