{"title":"Perfect.Sisters.2014.720p.BRRip.XviD.AC3-RARBG","uid":11088918,"size":3170118969,"categoryP":"video","categoryS":"movies","magnet":"?xt=urn:btih:cbc95cc7c67eb635879faf44947a71feadf74a78&amp;dn=Perfect.Sisters.2014.720p.BRRip.XviD.AC3-RARBG&amp;tr=udp%3A%2F%2Ftracker.openbittorrent.com%3A80&amp;tr=udp%3A%2F%2Fopen.demonii.com%3A1337&amp;tr=udp%3A%2F%2Ftracker.coppersurfer.tk%3A6969&amp;tr=udp%3A%2F%2Fexodus.desync.com%3A6969","seeders":0,"leechers":0,"uploader":"Drarbg","files":4,"time":1411494305,"description":" &lt;a href=&quot;https://rarbg.com&quot; rel=&quot;nofollow&quot; target=&quot;_NEW&quot;&gt;https://rarbg.com&lt;/a&gt;\n\nPerfect.Sisters.2014.720p.BRRip.XviD.AC3-RARBG\n\nAuto IMDB: &lt;a href=&quot;\nhttp://www.imdb.com/title/tt2027231/&quot; rel=&quot;nofollow&quot; target=&quot;_NEW&quot;&gt;\nhttp://www.imdb.com/title/tt2027231/&lt;/a&gt;\n\n-----------------------------------------\nScreens : &lt;a href=&quot;\nhttp://i.imgur.com/Wv9zOPK.png&quot; rel=&quot;nofollow&quot; target=&quot;_NEW&quot;&gt;\nhttp://i.imgur.com/Wv9zOPK.png&lt;/a&gt; &lt;a href=&quot;\nhttp://i.imgur.com/xHpgZhn.jpg&quot; rel=&quot;nofollow&quot; target=&quot;_NEW&quot;&gt;\nhttp://i.imgur.com/xHpgZhn.jpg&lt;/a&gt; &lt;a href=&quot;\nhttp://i.imgur.com/TkKjrYv.jpg&quot; rel=&quot;nofollow&quot; target=&quot;_NEW&quot;&gt;\nhttp://i.imgur.com/TkKjrYv.jpg&lt;/a&gt; &lt;a href=&quot;\nhttp://i.imgur.com/nURQPQV.png&quot; rel=&quot;nofollow&quot; target=&quot;_NEW&quot;&gt;\nhttp://i.imgur.com/nURQPQV.png&lt;/a&gt; &lt;a href=&quot;\nhttp://i.imgur.com/XN0qf2u.png&quot; rel=&quot;nofollow&quot; target=&quot;_NEW&quot;&gt;\nhttp://i.imgur.com/XN0qf2u.png&lt;/a&gt; &lt;a href=&quot;\nhttp://i.imgur.com/DW7x91P.png&quot; rel=&quot;nofollow&quot; target=&quot;_NEW&quot;&gt;\nhttp://i.imgur.com/DW7x91P.png&lt;/a&gt; &lt;a href=&quot;\nhttp://i.imgur.com/drcapsC.png&quot; rel=&quot;nofollow&quot; target=&quot;_NEW&quot;&gt;\nhttp://i.imgur.com/drcapsC.png&lt;/a&gt; &lt;a href=&quot;\nhttp://i.imgur.com/NoNZqp1.png&quot; rel=&quot;nofollow&quot; target=&quot;_NEW&quot;&gt;\nhttp://i.imgur.com/NoNZqp1.png&lt;/a&gt; &lt;a href=&quot;\nhttp://i.imgur.com/BCPGpF6.jpg&quot; rel=&quot;nofollow&quot; target=&quot;_NEW&quot;&gt;\nhttp://i.imgur.com/BCPGpF6.jpg&lt;/a&gt; &lt;a href=&quot;\nhttp://i.imgur.com/JwSxGaE.png&quot; rel=&quot;nofollow&quot; target=&quot;_NEW&quot;&gt;\nhttp://i.imgur.com/JwSxGaE.png&lt;/a&gt; &lt;a href=&quot;\nhttp://i.imgur.com/N8SOumo.png&quot; rel=&quot;nofollow&quot; target=&quot;_NEW&quot;&gt;\nhttp://i.imgur.com/N8SOumo.png&lt;/a&gt; &lt;a href=&quot;\nhttp://i.imgur.com/8A63TYw.png&quot; rel=&quot;nofollow&quot; target=&quot;_NEW&quot;&gt;\nhttp://i.imgur.com/8A63TYw.png&lt;/a&gt;\n\n-----------------------------------------\nAuto Media Info :\nVideo Format........: MPEG-4 Visual\nCodec ID............: XVID\nCodec ID/Hint.......: XviD\nLength..............: 1h36mn\nVideo...............: 1280x720 ( 25.000fps )\nBitrate.............: 3720Kbps\nAudio Format........: AC-3\nCodec ID............: 2000\nBit rate mode.......: Constant\nBitrate.............: 640Kbps\nChannel(s)..........: 6 channels\n\n","torrent":{"xt":"urn:btih:cbc95cc7c67eb635879faf44947a71feadf74a78","amp;dn":"Perfect.Sisters.2014.720p.BRRip.XviD.AC3-RARBG","amp;tr":["udp%3A%2F%2Ftracker.openbittorrent.com%3A80","udp%3A%2F%2Fopen.demonii.com%3A1337","udp%3A%2F%2Ftracker.coppersurfer.tk%3A6969","udp%3A%2F%2Fexodus.desync.com%3A6969"],"infoHash":"cbc95cc7c67eb635879faf44947a71feadf74a78","infoHashBuffer":{"type":"Buffer","data":[203,201,92,199,198,126,182,53,135,159,175,68,148,122,113,254,173,247,74,120]},"announce":[],"urlList":[]}}