{"title":"Derek.Acorahs.Ghost.Tour.2010.DVDRip.INTERNAL.X264-GHOULS","uid":12128823,"size":784785516,"categoryP":"video","categoryS":"movies","magnet":"?xt=urn:btih:ce97630580082fa02cda228cce589462fe09b813&amp;dn=Derek.Acorahs.Ghost.Tour.2010.DVDRip.INTERNAL.X264-GHOULS&amp;tr=udp%3A%2F%2Ftracker.openbittorrent.com%3A80&amp;tr=udp%3A%2F%2Fopen.demonii.com%3A1337&amp;tr=udp%3A%2F%2Ftracker.coppersurfer.tk%3A6969&amp;tr=udp%3A%2F%2Fexodus.desync.com%3A6969","seeders":0,"leechers":0,"uploader":"TvTeam","files":4,"time":1436986789,"description":"------------------------------------------------------------------------\n\n &lt;a href=&quot; https://www.torrenting.com&quot; rel=&quot;nofollow&quot; target=&quot;_NEW&quot;&gt; https://www.torrenting.com&lt;/a&gt;\n\nSign up is OPEN - for time being. Come and have fun.\n\n------------------------------------------------------------------------\n                                    |'.&quot;-._.-&quot;&quot;--.-&quot;-.__.-'/\n                                    |         .-.        (\n                                    |   |     (@.@)        )\n                                    |   |   '=.|m|.='      /\n                                    |  /    .='`&quot;``=.     /\n                                    |.'                  (\n            ()_                     |                     \n            {\\                     |        GHOULS        )\n            /;_)                    |                     /\n         =='/ &lt;===&lt;&lt;&lt;               |                    /\n            __                    |.-&quot;-.__.-&quot;&quot;-.__.-&quot;-.)\n\n                  GHOULS POSSESSES YOU WITH\nDerek.Acorahs.Ghost.Tour.2010.DVDRip.INTERNAL.X264-GHOULS\n\n    Title..........: Locomotion.Dan.Snows.History.Of.Railways.S01\n    Year...........: 2010\n    Rating.........: n/a\n    Genre..........: docu\n    URL............: http://www.amazon.co.uk/Derek-Acorah-Ghost-Tour-DVD/dp/B003ELKSI6\n\n    Release Date...: 17 May 2010\n    Duration.......: 1hr 11mn\n    Video..........: X264 1467kbps\n    Frame Rate.....: 25.000\n    Resolution.....: 720x404\n    Audio..........: 48.khz 2.0\n    Language.......: English\n    Subtitles......: n/a\n    Source.........: Retail R2 DVD\n    Size...........: 748 MB (784,777,478 bytes)\n    Files..........: 53x15 MB\n    \n\nDerek Acorah's remarkable gift has allowed him to enter a world inaccessible to most a world inhabited by the spirits of loved ones who have gone before us. Enjoy front row seats for Derek's nationwide tour as he connects to the 'other side' with the help of his spirit guide Sam, and delivers messages of love, hope and understanding. Amazed audience members are connected to family members and friends who have passed on and who offer wisdom, advice and comfort from beyond. A truly extraordinary programme in the presence of a truly extraordinary man. Included in the bonus features is an intimate 70 minute interview with Derek in the privacy and comfort of his own home. Derek openly and honestly answers all the questions his legions of fans regularly ask as he tours the country some with surprising answers! FREE CD To accompany this DVD event is a CD of music inspired by Derek's work which was specially created for him with his personal involvement to ensure it is in harmony with the spirit world. The 10 tracks selected offer the perfect ambiance for a peaceful, uplifting and spiritual experience.\n\n\n                                         d$$$$$$$$$$$c        ,c,\n                                        $$$$$$$$$$$$$b     ,d$$$L\n                                      c$$$$$$$$$$$$$$$b ,,d$$$$$$,\n                                   ,d$$$$$$$$$$$$?$$$$$$$J$$$$$$$$b    .\n                                  cF',,$$$$?$$$$$$`$$$$$$$$$$$$b&quot;$$$bcc$P\n                                ,d3$$$$$$$$$$c`?$$$ ?$$$$$$$$$$$&quot;  &quot;????&quot;\n                               ,dP&quot;&quot;&quot;$$$$$$$$$$$;$$$  `?$$$$$$$$&quot;\n                               ,$&quot;,zc$$$$$$P&quot;&quot;&quot;?$$$$P     &quot;?$$$F\n                             J$$d$$$$$$$$$$b. ,$$$$F\n                            d$P&quot;&quot;$$$$$$$$$$$&gt;d$$$$$\n                .,,,cccccccd$$c$cJ$$5$$$$$$$$$$$$$$\n              c$$$$$$$$$$$$$$$$&quot;&quot;&quot;P'$$c ?$$$$$$$$$F\n             $$$$$$&quot;)$$$$$$$$$$d$c`$$$$$z$$$$$$$dC\n             $$$$$$,c?$$$$$$$$$$$$$$$$$$$$$$$$$$$$$$b,\n             &quot;$$$$$$$b,?$$$$$$$$$$$$$$$cF&quot;$$$$$$$$$$$$$c\n               &quot;$$$$$$$bc,&quot;?$$$$$$$$$$$&quot; cc&quot;$$$$$$$$$$$$$c\n                 `&quot;?$$$$$$$c  &quot;&quot;&quot;??&quot;&quot;.,c$$$b$$$$$$$$$$$$$$,\n                    &quot;$c$$$$$eu wantedJ$$$$$$$$$$$$$$$$$$$$$\n             .,cc$$cc`$b?$$$F..   ..,$$$$$$$$$$$$$$$$$$$$$$\n           cd$$$$$$$$,?$b`$$$,`:::',$$$$$$$$P&quot;.,.`&quot;$$$$$P&quot;\n        ,c$$$$$$$$$$P$ $$b`$$$c,``,$$$$3$$$&quot;,$$$$$c`&quot;&quot;\n       c$$$$$$$$$$$$L?,?$$b ?$$$$$$$$F,$$$&quot;,$$$$$$$c\n     ,$$$$$$$$$$$$$$$?$ $$$$,&quot;$$$$$P&quot;d$$$ J$$$$$$$$$,\n   ,$$$$$$$$$?$$$$$$$ $ ?$$$$$c,,,,c$$$$FJ$$$$$$$$$$$\n ,d$$$$$$$$$&quot;d$$$$$$$ $L`$$$$$$$$$$$$$$$Fd$$$$$$$$$$$L\n $$$$$$$$$$F.$$$$$$$$ $$ ?$$$$$$$$$$$$$$;$$$$$$$$$$$$$\n $$$$$$$$$$ d$$$$$$$$ $$,`$$$$$$$$$$$$$$$$$$$$$$$$$$$$L\n $$$$$$$$$&quot;4$$$$$$$$$ $$$ $$$$$$$$$$$?$$$$$$$$$$$$$$$$$\n $$$$$$&quot;$$.$$$$$$$$$$ $$$,`$$$$$$$$$'d$$$$$$$$$$$$$$$$$h\n $$$$$$&lt;$F,$$$$$$$$$$ $$$$,`$$$$$$$'d$$$$$$$$$$$$$$$$$$$\n $$$$$$&lt;$ $$$$$$$$$$$ $$$$$,`$$$$&quot;,$$$$3$$$$$$$$$$$$$$$$h\n $$$$$$'F&lt;$$$$$$$$$$$ ?$$$$$c,&quot;&quot;,d$$$$'$$$$$$$$$$$$$$$$$$","torrent":{"xt":"urn:btih:ce97630580082fa02cda228cce589462fe09b813","amp;dn":"Derek.Acorahs.Ghost.Tour.2010.DVDRip.INTERNAL.X264-GHOULS","amp;tr":["udp%3A%2F%2Ftracker.openbittorrent.com%3A80","udp%3A%2F%2Fopen.demonii.com%3A1337","udp%3A%2F%2Ftracker.coppersurfer.tk%3A6969","udp%3A%2F%2Fexodus.desync.com%3A6969"],"infoHash":"ce97630580082fa02cda228cce589462fe09b813","infoHashBuffer":{"type":"Buffer","data":[206,151,99,5,128,8,47,160,44,218,34,140,206,88,148,98,254,9,184,19]},"announce":[],"urlList":[]}}