{"title":"TO TELL the TRUTH -- Who is the real baby photographer ?","uid":12153627,"size":68817327,"categoryP":"video","categoryS":"tv_shows","magnet":"?xt=urn:btih:d5b68234c2c80a9a5c2bf159e0952be2d2dc9da3&amp;dn=TO+TELL+the+TRUTH+--+Who+is+the+real+baby+photographer+%3F&amp;tr=udp%3A%2F%2Ftracker.openbittorrent.com%3A80&amp;tr=udp%3A%2F%2Fopen.demonii.com%3A1337&amp;tr=udp%3A%2F%2Ftracker.coppersurfer.tk%3A6969&amp;tr=udp%3A%2F%2Fexodus.desync.com%3A6969","seeders":0,"leechers":0,"uploader":"TheExecutive","files":1,"time":1437705745,"description":"Guest panelist :  Jack Paar","torrent":{"xt":"urn:btih:d5b68234c2c80a9a5c2bf159e0952be2d2dc9da3","amp;dn":"TO+TELL+the+TRUTH+--+Who+is+the+real+baby+photographer+%3F","amp;tr":["udp%3A%2F%2Ftracker.openbittorrent.com%3A80","udp%3A%2F%2Fopen.demonii.com%3A1337","udp%3A%2F%2Ftracker.coppersurfer.tk%3A6969","udp%3A%2F%2Fexodus.desync.com%3A6969"],"infoHash":"d5b68234c2c80a9a5c2bf159e0952be2d2dc9da3","infoHashBuffer":{"type":"Buffer","data":[213,182,130,52,194,200,10,154,92,43,241,89,224,149,43,226,210,220,157,163]},"announce":[],"urlList":[]}}