{"title":"3Darlings - Dr Busenstein - {Almerias}","uid":12124853,"size":40263791,"categoryP":"porn","categoryS":"other","magnet":"?xt=urn:btih:e6be53254eef64f8feaeb21b4c4208d3343f5175&amp;dn=3Darlings+-+Dr+Busenstein+-+%7BAlmerias%7D&amp;tr=udp%3A%2F%2Ftracker.openbittorrent.com%3A80&amp;tr=udp%3A%2F%2Fopen.demonii.com%3A1337&amp;tr=udp%3A%2F%2Ftracker.coppersurfer.tk%3A6969&amp;tr=udp%3A%2F%2Fexodus.desync.com%3A6969","seeders":0,"leechers":0,"uploader":"almeris","files":3,"time":1436908637,"description":"Size: 38,4 MB - Type: Full Color \n\nFormat: CBR - Resolution: 600x800 Aprox.   \n\nContains: 583 Pages - Language: English\n\n &lt;a href=&quot;\nhttp://s5.postimg.org/uj4xow193/image.jpg&quot; rel=&quot;nofollow&quot; target=&quot;_NEW&quot;&gt;\nhttp://s5.postimg.org/uj4xow193/image.jpg&lt;/a&gt;\n &lt;a href=&quot;\nhttp://s5.postimg.org/gqqit9ahj/image.jpg&quot; rel=&quot;nofollow&quot; target=&quot;_NEW&quot;&gt;\nhttp://s5.postimg.org/gqqit9ahj/image.jpg&lt;/a&gt;\n &lt;a href=&quot;\nhttp://s5.postimg.org/4enmfrmmv/image.jpg&quot; rel=&quot;nofollow&quot; target=&quot;_NEW&quot;&gt;\nhttp://s5.postimg.org/4enmfrmmv/image.jpg&lt;/a&gt;\n &lt;a href=&quot;\nhttp://s5.postimg.org/msy5jqyxj/image.jpg&quot; rel=&quot;nofollow&quot; target=&quot;_NEW&quot;&gt;\nhttp://s5.postimg.org/msy5jqyxj/image.jpg&lt;/a&gt;","torrent":{"xt":"urn:btih:e6be53254eef64f8feaeb21b4c4208d3343f5175","amp;dn":"3Darlings+-+Dr+Busenstein+-+%7BAlmerias%7D","amp;tr":["udp%3A%2F%2Ftracker.openbittorrent.com%3A80","udp%3A%2F%2Fopen.demonii.com%3A1337","udp%3A%2F%2Ftracker.coppersurfer.tk%3A6969","udp%3A%2F%2Fexodus.desync.com%3A6969"],"infoHash":"e6be53254eef64f8feaeb21b4c4208d3343f5175","infoHashBuffer":{"type":"Buffer","data":[230,190,83,37,78,239,100,248,254,174,178,27,76,66,8,211,52,63,81,117]},"announce":[],"urlList":[]}}