{"title":"Some.Teens.Exposed.From.Costa.Rica.XXX.iMAGESET-Ctrlme","uid":12287200,"size":6386034,"categoryP":"porn","categoryS":"pictures","magnet":"?xt=urn:btih:e9e8e70d742bce4e1b5e47e15acaacd351c44fc8&amp;dn=Some.Teens.Exposed.From.Costa.Rica.XXX.iMAGESET-Ctrlme&amp;tr=udp%3A%2F%2Ftracker.openbittorrent.com%3A80&amp;tr=udp%3A%2F%2Fopen.demonii.com%3A1337&amp;tr=udp%3A%2F%2Ftracker.coppersurfer.tk%3A6969&amp;tr=udp%3A%2F%2Fexodus.desync.com%3A6969","seeders":0,"leechers":1,"uploader":"Ctrlme","files":81,"time":1440486522,"description":"-----------------------------------------------------------\nSome.Teens.Exposed.From.Costa.Rica.XXX.iMAGESET-Ctrlme\n-----------------------------------------------------------\nScreenshots: &lt;a href=&quot;\nhttp://imgctrl.org/image/OEa&quot; rel=&quot;nofollow&quot; target=&quot;_NEW&quot;&gt;\nhttp://imgctrl.org/image/OEa&lt;/a&gt; &lt;a href=&quot;\nhttp://imgctrl.org/image/OE5&quot; rel=&quot;nofollow&quot; target=&quot;_NEW&quot;&gt;\nhttp://imgctrl.org/image/OE5&lt;/a&gt; &lt;a href=&quot;\nhttp://imgctrl.org/image/OEU&quot; rel=&quot;nofollow&quot; target=&quot;_NEW&quot;&gt;\nhttp://imgctrl.org/image/OEU&lt;/a&gt; &lt;a href=&quot;\nhttp://imgctrl.org/image/OEu&quot; rel=&quot;nofollow&quot; target=&quot;_NEW&quot;&gt;\nhttp://imgctrl.org/image/OEu&lt;/a&gt; &lt;a href=&quot;\nhttp://imgctrl.org/image/OE6&quot; rel=&quot;nofollow&quot; target=&quot;_NEW&quot;&gt;\nhttp://imgctrl.org/image/OE6&lt;/a&gt;\n-----------------------------------------------------------\n81 iMAGES\n-----------------------------------------------------------\nIf you like this torrent, please post a comment!\n\nDon't forget to seed!","torrent":{"xt":"urn:btih:e9e8e70d742bce4e1b5e47e15acaacd351c44fc8","amp;dn":"Some.Teens.Exposed.From.Costa.Rica.XXX.iMAGESET-Ctrlme","amp;tr":["udp%3A%2F%2Ftracker.openbittorrent.com%3A80","udp%3A%2F%2Fopen.demonii.com%3A1337","udp%3A%2F%2Ftracker.coppersurfer.tk%3A6969","udp%3A%2F%2Fexodus.desync.com%3A6969"],"infoHash":"e9e8e70d742bce4e1b5e47e15acaacd351c44fc8","infoHashBuffer":{"type":"Buffer","data":[233,232,231,13,116,43,206,78,27,94,71,225,90,202,172,211,81,196,79,200]},"announce":[],"urlList":[]}}