{"title":"Shadoman - Perilous Journey 1-5 + Office Politics 1-4 (Complete)","uid":12144659,"size":41253348,"categoryP":"porn","categoryS":"other","magnet":"?xt=urn:btih:e9ed516d5afd2e40c128a782618adab624c0b7e9&amp;dn=Shadoman+-+Perilous+Journey+1-5+%2B+Office+Politics+1-4+%28Complete%29&amp;tr=udp%3A%2F%2Ftracker.openbittorrent.com%3A80&amp;tr=udp%3A%2F%2Fopen.demonii.com%3A1337&amp;tr=udp%3A%2F%2Ftracker.coppersurfer.tk%3A6969&amp;tr=udp%3A%2F%2Fexodus.desync.com%3A6969","seeders":0,"leechers":0,"uploader":"almeris","files":4,"time":1437439687,"description":"Size: 39,3 MB - Type: Full Color \n\nFormat: CBR - Resolution: 1020x1320   \n\nContains: 217 Pages - Language: English\n\n &lt;a href=&quot;\nhttp://s5.postimg.org/x2o5zvzh3/image.jpg&quot; rel=&quot;nofollow&quot; target=&quot;_NEW&quot;&gt;\nhttp://s5.postimg.org/x2o5zvzh3/image.jpg&lt;/a&gt;\n &lt;a href=&quot;\nhttp://s5.postimg.org/ch9e7zhw7/image.jpg&quot; rel=&quot;nofollow&quot; target=&quot;_NEW&quot;&gt;\nhttp://s5.postimg.org/ch9e7zhw7/image.jpg&lt;/a&gt;\n &lt;a href=&quot;\nhttp://s5.postimg.org/af8wtqjx3/image.jpg&quot; rel=&quot;nofollow&quot; target=&quot;_NEW&quot;&gt;\nhttp://s5.postimg.org/af8wtqjx3/image.jpg&lt;/a&gt;\n &lt;a href=&quot;\nhttp://s5.postimg.org/rbxzm5rh3/image.jpg&quot; rel=&quot;nofollow&quot; target=&quot;_NEW&quot;&gt;\nhttp://s5.postimg.org/rbxzm5rh3/image.jpg&lt;/a&gt;","torrent":{"xt":"urn:btih:e9ed516d5afd2e40c128a782618adab624c0b7e9","amp;dn":"Shadoman+-+Perilous+Journey+1-5+%2B+Office+Politics+1-4+%28Complete%29","amp;tr":["udp%3A%2F%2Ftracker.openbittorrent.com%3A80","udp%3A%2F%2Fopen.demonii.com%3A1337","udp%3A%2F%2Ftracker.coppersurfer.tk%3A6969","udp%3A%2F%2Fexodus.desync.com%3A6969"],"infoHash":"e9ed516d5afd2e40c128a782618adab624c0b7e9","infoHashBuffer":{"type":"Buffer","data":[233,237,81,109,90,253,46,64,193,40,167,130,97,138,218,182,36,192,183,233]},"announce":[],"urlList":[]}}