{"title":"[NaughtyBookworms / NaughtyAmerica] Nina North (20127 / 25.08.1","uid":12292531,"size":2749432122,"categoryP":"porn","categoryS":"hd___movies","magnet":"?xt=urn:btih:f28e17ed12ce79f5c5ef7e94b6bc237deccdf0c7&amp;dn=+%5BNaughtyBookworms+%2F+NaughtyAmerica%5D+Nina+North+%2820127+%2F+25.08.1&amp;tr=udp%3A%2F%2Ftracker.openbittorrent.com%3A80&amp;tr=udp%3A%2F%2Fopen.demonii.com%3A1337&amp;tr=udp%3A%2F%2Ftracker.coppersurfer.tk%3A6969&amp;tr=udp%3A%2F%2Fexodus.desync.com%3A6969","seeders":0,"leechers":0,"uploader":"Chinu685","files":1,"time":1440575821,"description":" &lt;a href=&quot;http://milfimage.org/img-55dd557ea7d8b.html&quot; rel=&quot;nofollow&quot; target=&quot;_NEW&quot;&gt;http://milfimage.org/img-55dd557ea7d8b.html&lt;/a&gt;\n &lt;a href=&quot;\nhttp://milfimage.org/img-55dd5582500d2.html&quot; rel=&quot;nofollow&quot; target=&quot;_NEW&quot;&gt;\nhttp://milfimage.org/img-55dd5582500d2.html&lt;/a&gt;\n\n\n\n\n..:For more awesome stuff please click below:..                                 &lt;a href=&quot;\nhttps://thepiratebay.la/user/Chinu685/&quot; rel=&quot;nofollow&quot; target=&quot;_NEW&quot;&gt;\nhttps://thepiratebay.la/user/Chinu685/&lt;/a&gt;","torrent":{"xt":"urn:btih:f28e17ed12ce79f5c5ef7e94b6bc237deccdf0c7","amp;dn":"+%5BNaughtyBookworms+%2F+NaughtyAmerica%5D+Nina+North+%2820127+%2F+25.08.1","amp;tr":["udp%3A%2F%2Ftracker.openbittorrent.com%3A80","udp%3A%2F%2Fopen.demonii.com%3A1337","udp%3A%2F%2Ftracker.coppersurfer.tk%3A6969","udp%3A%2F%2Fexodus.desync.com%3A6969"],"infoHash":"f28e17ed12ce79f5c5ef7e94b6bc237deccdf0c7","infoHashBuffer":{"type":"Buffer","data":[242,142,23,237,18,206,121,245,197,239,126,148,182,188,35,125,236,205,240,199]},"announce":[],"urlList":[]}}