{"title":"linkin park-south side.mp3","uid":12221102,"size":9123134,"categoryP":"audio","categoryS":"music","magnet":"?xt=urn:btih:fa20e7c00204647ffc0d55e24e99911b1557ec11&amp;dn=linkin+park-south+side.mp3&amp;tr=udp%3A%2F%2Ftracker.openbittorrent.com%3A80&amp;tr=udp%3A%2F%2Fopen.demonii.com%3A1337&amp;tr=udp%3A%2F%2Ftracker.coppersurfer.tk%3A6969&amp;tr=udp%3A%2F%2Fexodus.desync.com%3A6969","seeders":0,"leechers":0,"uploader":"karter124","files":1,"time":1439365579,"description":"linkin park-south side","torrent":{"xt":"urn:btih:fa20e7c00204647ffc0d55e24e99911b1557ec11","amp;dn":"linkin+park-south+side.mp3","amp;tr":["udp%3A%2F%2Ftracker.openbittorrent.com%3A80","udp%3A%2F%2Fopen.demonii.com%3A1337","udp%3A%2F%2Ftracker.coppersurfer.tk%3A6969","udp%3A%2F%2Fexodus.desync.com%3A6969"],"infoHash":"fa20e7c00204647ffc0d55e24e99911b1557ec11","infoHashBuffer":{"type":"Buffer","data":[250,32,231,192,2,4,100,127,252,13,85,226,78,153,145,27,21,87,236,17]},"announce":[],"urlList":[]}}